joconst/__init__.py
joconst/constant.py
joconst/maps.py
joconst/object.py
joconst-0.1.14.dist-info/WHEEL
joconst-0.1.14.dist-info/METADATA
joconst-0.1.14.dist-info/RECORD
