Metadata-Version: 2.1
Name: joconst
Version: 0.1.14
Summary: 
Author: FangyangJz
Author-email: fangyang.jing@hotmail.com
Requires-Python: >=3.7.1,<4.0.0
Classifier: Programming Language :: Python :: 3
Classifier: Programming Language :: Python :: 3.10
Classifier: Programming Language :: Python :: 3.8
Classifier: Programming Language :: Python :: 3.9
Requires-Dist: jotdx (>=0.1.16,<0.2.0)
